killercoda_cli/__about__.py
killercoda_cli/__init__.py
killercoda_cli/assets.py
killercoda_cli/cli.py
killercoda_cli/file_operations.py
killercoda_cli/scenario_init.py
killercoda_cli/step_management.py
killercoda_cli/validation.py
killercoda_cli-1.3.0.dist-info/METADATA
killercoda_cli-1.3.0.dist-info/WHEEL
killercoda_cli-1.3.0.dist-info/entry_points.txt
killercoda_cli-1.3.0.dist-info/licenses/LICENSE.txt
killercoda_cli-1.3.0.dist-info/RECORD
