Metadata-Version: 2.1
Name: killercoda-cli
Version: 1.3.0
Summary: A CLI helper for writing killercoda scenarios and managing steps
Project-URL: Documentation, https://github.com/unknown/killercoda-cli#readme
Project-URL: Issues, https://github.com/unknown/killercoda-cli/issues
Project-URL: Source, https://github.com/unknown/killercoda-cli
Author-email: Piotr Zaniewski <piotrzan@gmail.com>
Classifier: Development Status :: 4 - Beta
Classifier: Programming Language :: Python
Classifier: Programming Language :: Python :: 3.8
Classifier: Programming Language :: Python :: 3.9
Classifier: Programming Language :: Python :: 3.10
Classifier: Programming Language :: Python :: 3.11
Classifier: Programming Language :: Python :: 3.12
Classifier: Programming Language :: Python :: Implementation :: CPython
Classifier: Programming Language :: Python :: Implementation :: PyPy
Requires-Python: >=3.8
Requires-Dist: cookiecutter
Requires-Dist: inquirer
